{
  "entityTrackingDistance": 64.0,
  "cacheCleanFrequency": 400,
  "hudEnabled": true,
  "hudTargetDistance": 64.0,
  "hudTargetGracePeriod": 10,
  "hudEntityRender": true,
  "hudBarRenderType": "BAR",
  "hudHealthBarSegments": true,
  "hudHealthBarLength": 100,
  "hudEntityDamageTint": true,
  "hudEntityName": true,
  "hudArmour": true,
  "hudEntityIcons": true,
  "hudPotionIcons": true,
  "hudOpacity": 1.0,
  "hudBarFontBackingOpacity": 0.5,
  "inWorldHudEnabled": true,
  "inWorldHUDActivation": "DAMAGED_AND_NEARBY",
  "inWorldHudOpacity": 1.0,
  "inWorldBarsRenderType": "COMBINED",
  "inWorldBarsLength": 50,
  "inWorldBarsSegments": false,
  "inWorldHudEntityName": true,
  "inWorldHudArmour": true,
  "inWorldHudEntityIcons": true,
  "inWorldHudPotionIcons": true,
  "inWorldHudNameOverride": true,
  "inWorldHudManualVerticalOffset": 0.0,
  "particlesEnabled": true,
  "particleDecimalPoints": 1,
  "particleScale": 1.0,
  "verbalHealthParticles": true,
  "damageParticleColour": 16776960,
  "healParticleColour": -16711936
}